{
    "key": "group_603d23c64253d",
    "title": "Post Type: Member",
    "fields": [
        {
            "key": "field_603d2434f8cee",
            "label": "Vitals",
            "name": "",
            "aria-label": "",
            "type": "tab",
            "instructions": "",
            "required": 0,
            "conditional_logic": 0,
            "wrapper": {
                "width": "",
                "class": "",
                "id": ""
            },
            "placement": "top",
            "endpoint": 0
        },
        {
            "key": "field_603d23ecce2e2",
            "label": "Vitals",
            "name": "vitals",
            "aria-label": "",
            "type": "group",
            "instructions": "",
            "required": 0,
            "conditional_logic": 0,
            "wrapper": {
                "width": "",
                "class": "",
                "id": ""
            },
            "layout": "block",
            "sub_fields": [
                {
                    "key": "field_603d23f6ce2e3",
                    "label": "First Name",
                    "name": "first_name",
                    "aria-label": "",
                    "type": "text",
                    "instructions": "",
                    "required": 0,
                    "conditional_logic": 0,
                    "wrapper": {
                        "width": "50",
                        "class": "",
                        "id": ""
                    },
                    "default_value": "",
                    "placeholder": "",
                    "prepend": "",
                    "append": "",
                    "maxlength": ""
                },
                {
                    "key": "field_603d23fdce2e4",
                    "label": "Last Name",
                    "name": "last_name",
                    "aria-label": "",
                    "type": "text",
                    "instructions": "",
                    "required": 0,
                    "conditional_logic": 0,
                    "wrapper": {
                        "width": "50",
                        "class": "",
                        "id": ""
                    },
                    "default_value": "",
                    "placeholder": "",
                    "prepend": "",
                    "append": "",
                    "maxlength": ""
                },
                {
                    "key": "field_603d2405ce2e5",
                    "label": "Hometown",
                    "name": "hometown",
                    "aria-label": "",
                    "type": "text",
                    "instructions": "",
                    "required": 0,
                    "conditional_logic": 0,
                    "wrapper": {
                        "width": "50",
                        "class": "",
                        "id": ""
                    },
                    "default_value": "",
                    "placeholder": "",
                    "prepend": "",
                    "append": "",
                    "maxlength": ""
                },
                {
                    "key": "field_603d240ece2e6",
                    "label": "Birthdate",
                    "name": "birthdate",
                    "aria-label": "",
                    "type": "date_picker",
                    "instructions": "",
                    "required": 0,
                    "conditional_logic": 0,
                    "wrapper": {
                        "width": "50",
                        "class": "",
                        "id": ""
                    },
                    "display_format": "m\/d\/Y",
                    "return_format": "Ymd",
                    "first_day": 1
                },
                {
                    "key": "field_60ae99551c081",
                    "label": "Date of Death",
                    "name": "date_of_death",
                    "aria-label": "",
                    "type": "date_picker",
                    "instructions": "",
                    "required": 0,
                    "conditional_logic": 0,
                    "wrapper": {
                        "width": "50",
                        "class": "",
                        "id": ""
                    },
                    "display_format": "m\/d\/Y",
                    "return_format": "Ymd",
                    "first_day": 1
                }
            ]
        },
        {
            "key": "field_603d2448f8cef",
            "label": "Biography",
            "name": "",
            "aria-label": "",
            "type": "tab",
            "instructions": "",
            "required": 0,
            "conditional_logic": 0,
            "wrapper": {
                "width": "",
                "class": "",
                "id": ""
            },
            "placement": "top",
            "endpoint": 0
        },
        {
            "key": "field_603d244ff8cf0",
            "label": "Biography",
            "name": "biography",
            "aria-label": "",
            "type": "wysiwyg",
            "instructions": "",
            "required": 0,
            "conditional_logic": 0,
            "wrapper": {
                "width": "",
                "class": "",
                "id": ""
            },
            "default_value": "",
            "tabs": "all",
            "toolbar": "full",
            "media_upload": 0,
            "delay": 0
        },
        {
            "key": "field_603d2467f8cf1",
            "label": "Career",
            "name": "",
            "aria-label": "",
            "type": "tab",
            "instructions": "",
            "required": 0,
            "conditional_logic": 0,
            "wrapper": {
                "width": "",
                "class": "",
                "id": ""
            },
            "placement": "top",
            "endpoint": 0
        },
        {
            "key": "field_603d252cf8d01",
            "label": "Playing Career",
            "name": "playing_career",
            "aria-label": "",
            "type": "repeater",
            "instructions": "",
            "required": 0,
            "conditional_logic": 0,
            "wrapper": {
                "width": "",
                "class": "",
                "id": ""
            },
            "collapsed": "",
            "min": 0,
            "max": 0,
            "layout": "table",
            "button_label": "+ Add Team",
            "sub_fields": [
                {
                    "key": "field_603d252cf8d04",
                    "label": "Year",
                    "name": "year",
                    "aria-label": "",
                    "type": "text",
                    "instructions": "",
                    "required": 0,
                    "conditional_logic": 0,
                    "wrapper": {
                        "width": "25",
                        "class": "",
                        "id": ""
                    },
                    "default_value": "",
                    "placeholder": "",
                    "prepend": "",
                    "append": "",
                    "maxlength": "",
                    "parent_repeater": "field_603d252cf8d01"
                },
                {
                    "key": "field_603d252cf8d02",
                    "label": "Team",
                    "name": "team",
                    "aria-label": "",
                    "type": "post_object",
                    "instructions": "",
                    "required": 0,
                    "conditional_logic": 0,
                    "wrapper": {
                        "width": "",
                        "class": "",
                        "id": ""
                    },
                    "post_type": [
                        "team"
                    ],
                    "taxonomy": "",
                    "allow_null": 0,
                    "multiple": 0,
                    "return_format": "object",
                    "ui": 1,
                    "parent_repeater": "field_603d252cf8d01"
                },
                {
                    "key": "field_605e3ee9bd6f7",
                    "label": "Note",
                    "name": "note",
                    "aria-label": "",
                    "type": "text",
                    "instructions": "",
                    "required": 0,
                    "conditional_logic": 0,
                    "wrapper": {
                        "width": "",
                        "class": "",
                        "id": ""
                    },
                    "default_value": "",
                    "placeholder": "",
                    "prepend": "",
                    "append": "",
                    "maxlength": "",
                    "parent_repeater": "field_603d252cf8d01"
                }
            ],
            "rows_per_page": 20
        },
        {
            "key": "field_603d2499f8cf2",
            "label": "US Championships",
            "name": "us_championships",
            "aria-label": "",
            "type": "repeater",
            "instructions": "",
            "required": 0,
            "conditional_logic": 0,
            "wrapper": {
                "width": "",
                "class": "",
                "id": ""
            },
            "collapsed": "",
            "min": 0,
            "max": 0,
            "layout": "table",
            "button_label": "+ Add Tournament",
            "sub_fields": [
                {
                    "key": "field_60528acf4152b",
                    "label": "Team",
                    "name": "team",
                    "aria-label": "",
                    "type": "post_object",
                    "instructions": "",
                    "required": 0,
                    "conditional_logic": 0,
                    "wrapper": {
                        "width": "",
                        "class": "",
                        "id": ""
                    },
                    "post_type": [
                        "team"
                    ],
                    "taxonomy": "",
                    "allow_null": 0,
                    "multiple": 0,
                    "return_format": "object",
                    "ui": 1,
                    "parent_repeater": "field_603d2499f8cf2"
                },
                {
                    "key": "field_603eaa1044b5d",
                    "label": "Tournament",
                    "name": "tournament",
                    "aria-label": "",
                    "type": "post_object",
                    "instructions": "",
                    "required": 0,
                    "conditional_logic": 0,
                    "wrapper": {
                        "width": "",
                        "class": "",
                        "id": ""
                    },
                    "post_type": [
                        "tournaments"
                    ],
                    "taxonomy": "",
                    "allow_null": 0,
                    "multiple": 0,
                    "return_format": "object",
                    "ui": 1,
                    "parent_repeater": "field_603d2499f8cf2"
                },
                {
                    "key": "field_603eaa67ed37c",
                    "label": "Placement",
                    "name": "placement",
                    "aria-label": "",
                    "type": "select",
                    "instructions": "",
                    "required": 0,
                    "conditional_logic": 0,
                    "wrapper": {
                        "width": "",
                        "class": "",
                        "id": ""
                    },
                    "choices": {
                        "1st": "1st",
                        "2nd": "2nd",
                        "3rd": "3rd",
                        "4th": "4th",
                        "5th": "5th",
                        "6th": "6th",
                        "7th": "7th",
                        "8th": "8th",
                        "9th": "9th",
                        "10th": "10th",
                        "11th": "11th",
                        "12th": "12th",
                        "13th": "13th",
                        "14th": "14th",
                        "15th": "15th",
                        "16th": "16th",
                        "Pool Play": "Pool Play",
                        "Power Pools": "Power Pools",
                        "Pre-Quarterfinals": "Pre-Quarterfinals",
                        "Quarterfinals": "Quarterfinals",
                        "Semifinals": "Semifinals",
                        "Finals": "Finals",
                        "Regionals": "Regionals",
                        "Sectionals": "Sectionals",
                        "1st Round": "1st Round",
                        "2nd Round": "2nd Round",
                        "3rd Round": "3rd Round",
                        "4th Round": "4th Round"
                    },
                    "default_value": false,
                    "allow_null": 0,
                    "multiple": 0,
                    "ui": 0,
                    "return_format": "value",
                    "ajax": 0,
                    "placeholder": "",
                    "parent_repeater": "field_603d2499f8cf2"
                }
            ],
            "rows_per_page": 20
        },
        {
            "key": "field_603d24cff8cf8",
            "label": "WFDF Championships",
            "name": "wfdf_championships",
            "aria-label": "",
            "type": "repeater",
            "instructions": "",
            "required": 0,
            "conditional_logic": 0,
            "wrapper": {
                "width": "",
                "class": "",
                "id": ""
            },
            "collapsed": "",
            "min": 0,
            "max": 0,
            "layout": "table",
            "button_label": "+ Add Tournament",
            "sub_fields": [
                {
                    "key": "field_60528b0904ec0",
                    "label": "Team",
                    "name": "team",
                    "aria-label": "",
                    "type": "post_object",
                    "instructions": "",
                    "required": 0,
                    "conditional_logic": 0,
                    "wrapper": {
                        "width": "",
                        "class": "",
                        "id": ""
                    },
                    "post_type": [
                        "team"
                    ],
                    "taxonomy": "",
                    "allow_null": 0,
                    "multiple": 0,
                    "return_format": "object",
                    "ui": 1,
                    "parent_repeater": "field_603d24cff8cf8"
                },
                {
                    "key": "field_603ea8c9259e9",
                    "label": "Tournament",
                    "name": "tournament",
                    "aria-label": "",
                    "type": "post_object",
                    "instructions": "",
                    "required": 0,
                    "conditional_logic": 0,
                    "wrapper": {
                        "width": "",
                        "class": "",
                        "id": ""
                    },
                    "post_type": [
                        "tournaments"
                    ],
                    "taxonomy": "",
                    "allow_null": 0,
                    "multiple": 0,
                    "return_format": "object",
                    "ui": 1,
                    "parent_repeater": "field_603d24cff8cf8"
                },
                {
                    "key": "field_603d24cff8cfd",
                    "label": "Placement",
                    "name": "placement",
                    "aria-label": "",
                    "type": "select",
                    "instructions": "",
                    "required": 0,
                    "conditional_logic": 0,
                    "wrapper": {
                        "width": "",
                        "class": "",
                        "id": ""
                    },
                    "choices": {
                        "1st": "1st",
                        "2nd": "2nd",
                        "3rd": "3rd",
                        "4th": "4th",
                        "5th": "5th",
                        "6th": "6th",
                        "7th": "7th",
                        "8th": "8th",
                        "9th": "9th",
                        "10th": "10th",
                        "11th": "11th",
                        "12th": "12th",
                        "13th": "13th",
                        "14th": "14th",
                        "15th": "15th",
                        "16th": "16th",
                        "Pool Play": "Pool Play",
                        "Power Pools": "Power Pools",
                        "Pre-Quarterfinals": "Pre-Quarterfinals",
                        "Quarterfinals": "Quarterfinals",
                        "Semifinals": "Semifinals",
                        "Finals": "Finals",
                        "1st Round": "1st Round",
                        "2nd Round": "2nd Round",
                        "3rd Round": "3rd Round",
                        "4th Round": "4th Round"
                    },
                    "default_value": false,
                    "allow_null": 0,
                    "multiple": 0,
                    "ui": 0,
                    "return_format": "value",
                    "ajax": 0,
                    "placeholder": "",
                    "parent_repeater": "field_603d24cff8cf8"
                }
            ],
            "rows_per_page": 20
        },
        {
            "key": "field_60a3e3a643140",
            "label": "Pro Seasons",
            "name": "pro_seasons",
            "aria-label": "",
            "type": "repeater",
            "instructions": "",
            "required": 0,
            "conditional_logic": 0,
            "wrapper": {
                "width": "",
                "class": "",
                "id": ""
            },
            "collapsed": "",
            "min": 0,
            "max": 0,
            "layout": "table",
            "button_label": "+ Add Tournament",
            "sub_fields": [
                {
                    "key": "field_60a3e3a743141",
                    "label": "Team",
                    "name": "team",
                    "aria-label": "",
                    "type": "post_object",
                    "instructions": "",
                    "required": 0,
                    "conditional_logic": 0,
                    "wrapper": {
                        "width": "",
                        "class": "",
                        "id": ""
                    },
                    "post_type": [
                        "team"
                    ],
                    "taxonomy": "",
                    "allow_null": 0,
                    "multiple": 0,
                    "return_format": "object",
                    "ui": 1,
                    "parent_repeater": "field_60a3e3a643140"
                },
                {
                    "key": "field_60a3e3a743142",
                    "label": "Season",
                    "name": "season",
                    "aria-label": "",
                    "type": "post_object",
                    "instructions": "",
                    "required": 0,
                    "conditional_logic": 0,
                    "wrapper": {
                        "width": "",
                        "class": "",
                        "id": ""
                    },
                    "post_type": [
                        "tournaments"
                    ],
                    "taxonomy": "",
                    "allow_null": 0,
                    "multiple": 0,
                    "return_format": "object",
                    "ui": 1,
                    "parent_repeater": "field_60a3e3a643140"
                },
                {
                    "key": "field_60a3e3a743143",
                    "label": "Placement",
                    "name": "placement",
                    "aria-label": "",
                    "type": "select",
                    "instructions": "",
                    "required": 0,
                    "conditional_logic": 0,
                    "wrapper": {
                        "width": "",
                        "class": "",
                        "id": ""
                    },
                    "choices": {
                        "1st": "1st",
                        "2nd": "2nd",
                        "3rd": "3rd",
                        "4th": "4th",
                        "5th": "5th",
                        "6th": "6th",
                        "7th": "7th",
                        "8th": "8th",
                        "9th": "9th",
                        "10th": "10th",
                        "11th": "11th",
                        "12th": "12th",
                        "13th": "13th",
                        "14th": "14th",
                        "15th": "15th",
                        "16th": "16th",
                        "Pool Play": "Pool Play",
                        "Power Pools": "Power Pools",
                        "Pre-Quarterfinals": "Pre-Quarterfinals",
                        "Quarterfinals": "Quarterfinals",
                        "Semifinals": "Semifinals",
                        "Finals": "Finals",
                        "Playoffs": "Playoffs",
                        "Missed Playoffs": "Missed Playoffs",
                        "1st Round": "1st Round",
                        "2nd Round": "2nd Round",
                        "3rd Round": "3rd Round",
                        "4th Round": "4th Round"
                    },
                    "default_value": false,
                    "allow_null": 0,
                    "multiple": 0,
                    "ui": 0,
                    "return_format": "value",
                    "ajax": 0,
                    "placeholder": "",
                    "parent_repeater": "field_60a3e3a643140"
                }
            ],
            "rows_per_page": 20
        },
        {
            "key": "field_603d24e0f8cfe",
            "label": "Contributions and Service",
            "name": "contributions_and_service",
            "aria-label": "",
            "type": "repeater",
            "instructions": "",
            "required": 0,
            "conditional_logic": 0,
            "wrapper": {
                "width": "",
                "class": "",
                "id": ""
            },
            "collapsed": "",
            "min": 0,
            "max": 0,
            "layout": "table",
            "button_label": "+ Add Entry",
            "sub_fields": [
                {
                    "key": "field_603d24eff8cff",
                    "label": "Year",
                    "name": "year",
                    "aria-label": "",
                    "type": "text",
                    "instructions": "",
                    "required": 0,
                    "conditional_logic": 0,
                    "wrapper": {
                        "width": "20",
                        "class": "",
                        "id": ""
                    },
                    "default_value": "",
                    "placeholder": "",
                    "prepend": "",
                    "append": "",
                    "maxlength": "",
                    "parent_repeater": "field_603d24e0f8cfe"
                },
                {
                    "key": "field_603d24f2f8d00",
                    "label": "Description",
                    "name": "description",
                    "aria-label": "",
                    "type": "text",
                    "instructions": "",
                    "required": 0,
                    "conditional_logic": 0,
                    "wrapper": {
                        "width": "",
                        "class": "",
                        "id": ""
                    },
                    "default_value": "",
                    "placeholder": "",
                    "prepend": "",
                    "append": "",
                    "maxlength": "",
                    "parent_repeater": "field_603d24e0f8cfe"
                }
            ],
            "rows_per_page": 20
        },
        {
            "key": "field_6052909faef55",
            "label": "Awards",
            "name": "awards",
            "aria-label": "",
            "type": "repeater",
            "instructions": "",
            "required": 0,
            "conditional_logic": 0,
            "wrapper": {
                "width": "",
                "class": "",
                "id": ""
            },
            "collapsed": "",
            "min": 0,
            "max": 0,
            "layout": "table",
            "button_label": "+ Add Award",
            "sub_fields": [
                {
                    "key": "field_605290a5aef56",
                    "label": "Year",
                    "name": "year",
                    "aria-label": "",
                    "type": "post_object",
                    "instructions": "",
                    "required": 0,
                    "conditional_logic": 0,
                    "wrapper": {
                        "width": "25",
                        "class": "",
                        "id": ""
                    },
                    "post_type": [
                        "year"
                    ],
                    "taxonomy": "",
                    "allow_null": 0,
                    "multiple": 0,
                    "return_format": "object",
                    "ui": 1,
                    "parent_repeater": "field_6052909faef55"
                },
                {
                    "key": "field_605290bfaef57",
                    "label": "Award",
                    "name": "award",
                    "aria-label": "",
                    "type": "text",
                    "instructions": "",
                    "required": 0,
                    "conditional_logic": 0,
                    "wrapper": {
                        "width": "",
                        "class": "",
                        "id": ""
                    },
                    "default_value": "",
                    "placeholder": "",
                    "prepend": "",
                    "append": "",
                    "maxlength": "",
                    "parent_repeater": "field_6052909faef55"
                }
            ],
            "rows_per_page": 20
        },
        {
            "key": "field_603d255bf8d07",
            "label": "Interview",
            "name": "",
            "aria-label": "",
            "type": "tab",
            "instructions": "",
            "required": 0,
            "conditional_logic": 0,
            "wrapper": {
                "width": "",
                "class": "",
                "id": ""
            },
            "placement": "top",
            "endpoint": 0
        },
        {
            "key": "field_603d2563f8d08",
            "label": "Interview",
            "name": "interview",
            "aria-label": "",
            "type": "flexible_content",
            "instructions": "",
            "required": 0,
            "conditional_logic": 0,
            "wrapper": {
                "width": "",
                "class": "",
                "id": ""
            },
            "layouts": {
                "layout_603d256a08de8": {
                    "key": "layout_603d256a08de8",
                    "name": "qa",
                    "label": "Q & A",
                    "display": "block",
                    "sub_fields": [
                        {
                            "key": "field_603d2579f8d09",
                            "label": "Question",
                            "name": "question",
                            "aria-label": "",
                            "type": "textarea",
                            "instructions": "",
                            "required": 0,
                            "conditional_logic": 0,
                            "wrapper": {
                                "width": "",
                                "class": "",
                                "id": ""
                            },
                            "default_value": "",
                            "placeholder": "",
                            "maxlength": "",
                            "rows": 3,
                            "new_lines": "br"
                        },
                        {
                            "key": "field_603d2582f8d0a",
                            "label": "Answer",
                            "name": "answer",
                            "aria-label": "",
                            "type": "wysiwyg",
                            "instructions": "",
                            "required": 0,
                            "conditional_logic": 0,
                            "wrapper": {
                                "width": "",
                                "class": "",
                                "id": ""
                            },
                            "default_value": "",
                            "tabs": "all",
                            "toolbar": "full",
                            "media_upload": 0,
                            "delay": 0
                        },
                        {
                            "key": "field_605294e5a4820",
                            "label": "Photo",
                            "name": "photo",
                            "aria-label": "",
                            "type": "image",
                            "instructions": "",
                            "required": 0,
                            "conditional_logic": 0,
                            "wrapper": {
                                "width": "",
                                "class": "",
                                "id": ""
                            },
                            "return_format": "array",
                            "preview_size": "medium",
                            "library": "all",
                            "min_width": "",
                            "min_height": "",
                            "min_size": "",
                            "max_width": "",
                            "max_height": "",
                            "max_size": "",
                            "mime_types": ""
                        }
                    ],
                    "min": "",
                    "max": ""
                }
            },
            "button_label": "+ Add Question",
            "min": "",
            "max": ""
        },
        {
            "key": "field_60528fe97b4b0",
            "label": "Letters of Recommendation",
            "name": "",
            "aria-label": "",
            "type": "tab",
            "instructions": "",
            "required": 0,
            "conditional_logic": 0,
            "wrapper": {
                "width": "",
                "class": "",
                "id": ""
            },
            "placement": "top",
            "endpoint": 0
        },
        {
            "key": "field_60528ff67b4b1",
            "label": "Letters of Recommendation",
            "name": "letters_of_recommendation",
            "aria-label": "",
            "type": "flexible_content",
            "instructions": "",
            "required": 0,
            "conditional_logic": 0,
            "wrapper": {
                "width": "",
                "class": "",
                "id": ""
            },
            "layouts": {
                "layout_603d256a08de8": {
                    "key": "layout_603d256a08de8",
                    "name": "letter",
                    "label": "Letter",
                    "display": "block",
                    "sub_fields": [
                        {
                            "key": "field_6052900a7b4b4",
                            "label": "Text",
                            "name": "text",
                            "aria-label": "",
                            "type": "wysiwyg",
                            "instructions": "",
                            "required": 0,
                            "conditional_logic": 0,
                            "wrapper": {
                                "width": "",
                                "class": "",
                                "id": ""
                            },
                            "default_value": "",
                            "tabs": "all",
                            "toolbar": "full",
                            "media_upload": 0,
                            "delay": 0
                        },
                        {
                            "key": "field_605290137b4b5",
                            "label": "Recommender",
                            "name": "recommender",
                            "aria-label": "",
                            "type": "text",
                            "instructions": "",
                            "required": 0,
                            "conditional_logic": 0,
                            "wrapper": {
                                "width": "",
                                "class": "",
                                "id": ""
                            },
                            "default_value": "",
                            "placeholder": "",
                            "prepend": "",
                            "append": "",
                            "maxlength": ""
                        },
                        {
                            "key": "field_60529211a878a",
                            "label": "Photo",
                            "name": "photo",
                            "aria-label": "",
                            "type": "image",
                            "instructions": "",
                            "required": 0,
                            "conditional_logic": 0,
                            "wrapper": {
                                "width": "",
                                "class": "",
                                "id": ""
                            },
                            "return_format": "array",
                            "preview_size": "medium",
                            "library": "all",
                            "min_width": "",
                            "min_height": "",
                            "min_size": "",
                            "max_width": "",
                            "max_height": "",
                            "max_size": "",
                            "mime_types": ""
                        }
                    ],
                    "min": "",
                    "max": ""
                }
            },
            "button_label": "+ Add Letter",
            "min": "",
            "max": ""
        },
        {
            "key": "field_603d25a2d5694",
            "label": "Media",
            "name": "",
            "aria-label": "",
            "type": "tab",
            "instructions": "",
            "required": 0,
            "conditional_logic": 0,
            "wrapper": {
                "width": "",
                "class": "",
                "id": ""
            },
            "placement": "top",
            "endpoint": 0
        },
        {
            "key": "field_603d25b7d5696",
            "label": "Photos",
            "name": "photos",
            "aria-label": "",
            "type": "group",
            "instructions": "",
            "required": 0,
            "conditional_logic": 0,
            "wrapper": {
                "width": "",
                "class": "",
                "id": ""
            },
            "layout": "block",
            "sub_fields": [
                {
                    "key": "field_603d25a7d5695",
                    "label": "Headshot",
                    "name": "headshot",
                    "aria-label": "",
                    "type": "image",
                    "instructions": "",
                    "required": 0,
                    "conditional_logic": 0,
                    "wrapper": {
                        "width": "",
                        "class": "",
                        "id": ""
                    },
                    "return_format": "array",
                    "preview_size": "medium",
                    "library": "all",
                    "min_width": "",
                    "min_height": "",
                    "min_size": "",
                    "max_width": "",
                    "max_height": "",
                    "max_size": "",
                    "mime_types": ""
                },
                {
                    "key": "field_603d25c6d5698",
                    "label": "Player Card",
                    "name": "player_card",
                    "aria-label": "",
                    "type": "image",
                    "instructions": "",
                    "required": 0,
                    "conditional_logic": 0,
                    "wrapper": {
                        "width": "",
                        "class": "",
                        "id": ""
                    },
                    "return_format": "array",
                    "preview_size": "medium",
                    "library": "all",
                    "min_width": "",
                    "min_height": "",
                    "min_size": "",
                    "max_width": "",
                    "max_height": "",
                    "max_size": "",
                    "mime_types": ""
                }
            ]
        },
        {
            "key": "field_60529225e2c90",
            "label": "Gallery",
            "name": "gallery",
            "aria-label": "",
            "type": "gallery",
            "instructions": "",
            "required": 0,
            "conditional_logic": 0,
            "wrapper": {
                "width": "",
                "class": "",
                "id": ""
            },
            "return_format": "array",
            "preview_size": "medium",
            "insert": "append",
            "library": "all",
            "min": "",
            "max": "",
            "min_width": "",
            "min_height": "",
            "min_size": "",
            "max_width": "",
            "max_height": "",
            "max_size": "",
            "mime_types": ""
        },
        {
            "key": "field_603d25d4d5699",
            "label": "Meta",
            "name": "",
            "aria-label": "",
            "type": "tab",
            "instructions": "",
            "required": 0,
            "conditional_logic": 0,
            "wrapper": {
                "width": "",
                "class": "",
                "id": ""
            },
            "placement": "top",
            "endpoint": 0
        },
        {
            "key": "field_603d25dbd569a",
            "label": "Meta",
            "name": "meta",
            "aria-label": "",
            "type": "group",
            "instructions": "",
            "required": 0,
            "conditional_logic": 0,
            "wrapper": {
                "width": "",
                "class": "",
                "id": ""
            },
            "layout": "block",
            "sub_fields": [
                {
                    "key": "field_603d25e0d569b",
                    "label": "Induction Type",
                    "name": "induction_type",
                    "aria-label": "",
                    "type": "button_group",
                    "instructions": "",
                    "required": 0,
                    "conditional_logic": 0,
                    "wrapper": {
                        "width": "50",
                        "class": "",
                        "id": ""
                    },
                    "choices": {
                        "player": "Player",
                        "contributor": "Contributor",
                        "special-merit": "Special Merit"
                    },
                    "allow_null": 0,
                    "default_value": "",
                    "layout": "horizontal",
                    "return_format": "array"
                },
                {
                    "key": "field_603d261e08b2c",
                    "label": "Class",
                    "name": "class",
                    "aria-label": "",
                    "type": "post_object",
                    "instructions": "",
                    "required": 0,
                    "conditional_logic": 0,
                    "wrapper": {
                        "width": "50",
                        "class": "",
                        "id": ""
                    },
                    "post_type": [
                        "year"
                    ],
                    "taxonomy": "",
                    "allow_null": 0,
                    "multiple": 0,
                    "return_format": "object",
                    "ui": 1
                },
                {
                    "key": "field_603d29fb3f3f5",
                    "label": "Years Active",
                    "name": "years_active",
                    "aria-label": "",
                    "type": "relationship",
                    "instructions": "",
                    "required": 0,
                    "conditional_logic": 0,
                    "wrapper": {
                        "width": "",
                        "class": "years-rel",
                        "id": ""
                    },
                    "post_type": [
                        "year"
                    ],
                    "taxonomy": "",
                    "filters": "",
                    "elements": "",
                    "min": "",
                    "max": "",
                    "return_format": "object"
                },
                {
                    "key": "field_60528f187c47d",
                    "label": "Divisions",
                    "name": "divisions",
                    "aria-label": "",
                    "type": "relationship",
                    "instructions": "",
                    "required": 0,
                    "conditional_logic": 0,
                    "wrapper": {
                        "width": "",
                        "class": "div-rel",
                        "id": ""
                    },
                    "post_type": [
                        "division"
                    ],
                    "taxonomy": "",
                    "filters": [
                        "search"
                    ],
                    "elements": "",
                    "min": "",
                    "max": "",
                    "return_format": "object"
                }
            ]
        }
    ],
    "location": [
        [
            {
                "param": "post_type",
                "operator": "==",
                "value": "member"
            },
            {
                "param": "post_template",
                "operator": "==",
                "value": "default"
            }
        ]
    ],
    "menu_order": 0,
    "position": "normal",
    "style": "seamless",
    "label_placement": "top",
    "instruction_placement": "label",
    "hide_on_screen": [
        "the_content",
        "excerpt",
        "discussion",
        "comments",
        "revisions",
        "slug",
        "author",
        "format",
        "featured_image",
        "categories",
        "tags",
        "send-trackbacks"
    ],
    "active": true,
    "description": "",
    "show_in_rest": 0,
    "modified": 1669227701
}